gtfs_parser/__init__.py
gtfs_parser/__main__.py
gtfs_parser/aggregate.py
gtfs_parser/gtfs.py
gtfs_parser/parse.py
gtfs_parser-0.2.2.dist-info/LICENSE
gtfs_parser-0.2.2.dist-info/METADATA
gtfs_parser-0.2.2.dist-info/WHEEL
gtfs_parser-0.2.2.dist-info/entry_points.txt
gtfs_parser-0.2.2.dist-info/RECORD
