Metadata-Version: 2.1
Name: gtfs_parser
Version: 0.2.2
Summary: parse and aggregate GTFS
Home-page: https://github.com/MIERUNE
License: MIT
Author: MIERUNE Inc.
Requires-Python: >=3.9.0
Classifier: License :: OSI Approved :: MIT License
Classifier: Programming Language :: Python :: 3
Classifier: Programming Language :: Python :: 3.9
Classifier: Programming Language :: Python :: 3.10
Classifier: Programming Language :: Python :: 3.11
Classifier: Programming Language :: Python :: 3.12
Requires-Dist: pandas (>=1.3.3)
Project-URL: Repository, https://github.com/MIERUNE/gtfs-parser
